sql2json/__init__.py
sql2json/__main__.py
sql2json/parameter/__init__.py
sql2json/parameter/parameter_parser.py
sql2json/sql2json.py
sql2json-0.1.10.dist-info/WHEEL
sql2json-0.1.10.dist-info/METADATA
sql2json-0.1.10.dist-info/RECORD
